log_parser2/__init__.py
log_parser2/__main__.py
log_parser2/__version__.py
log_parser2/cli/__init__.py
log_parser2/cli/__main__.py
log_parser2/cli/cli.py
log_parser2/cli/patterns.py
log_parser2/db_provider.py
log_parser2/log_parser2.py
log_parser2/logging.py
log_parser2/showcase/__init__.py
log_parser2/showcase/__main__.py
log_parser2/showcase/access.log
log_parser2/showcase/showcase.py
taskp5-2.1.2.dist-info/entry_points.txt
taskp5-2.1.2.dist-info/LICENSE
taskp5-2.1.2.dist-info/METADATA
taskp5-2.1.2.dist-info/WHEEL
taskp5-2.1.2.dist-info/RECORD
