Metadata-Version: 2.1
Name: taskp5
Version: 2.1.2
Summary: Log file parser CLI and library (v.2)
License: MIT
Author: Bill.Avramenko
Author-email: billavramenko@gmail.com
Requires-Python: >=3.8,<4.0
Classifier: License :: OSI Approved :: MIT License
Classifier: Programming Language :: Python :: 3
Classifier: Programming Language :: Python :: 3.8
Classifier: Programming Language :: Python :: 3.9
Classifier: Programming Language :: Python :: 3.10
Classifier: Programming Language :: Python :: 3.11
Requires-Dist: mysql-connector-python (>=8.1.0,<9.0.0)
Requires-Dist: psycopg2 (>=2.9.7,<3.0.0)
Requires-Dist: pymongo (>=4.4.1,<5.0.0)
Requires-Dist: questionary (>=2.0.0,<3.0.0)
